beta4dist/__init__.py
beta4dist/beta4_model.py
beta4dist/distribution.py
beta4dist-0.3.3.dist-info/LICENSE
beta4dist-0.3.3.dist-info/METADATA
beta4dist-0.3.3.dist-info/WHEEL
beta4dist-0.3.3.dist-info/top_level.txt
beta4dist-0.3.3.dist-info/RECORD
