Metadata-Version: 2.1
Name: beta4dist
Version: 0.3.3
Summary: A Python package for the Four-Parameter Beta Distribution and Likelihood-Based Estimation
Home-page: https://github.com/soham39039820/beta4dist
Author: Soham Ghosh
Author-email: phd2001161004@iiti.ac.in
License: MIT
Project-URL: Documentation, https://github.com/soham39039820/beta4dist#readme
Project-URL: Source, https://github.com/soham39039820/beta4dist
Project-URL: Tracker, https://github.com/soham39039820/beta4dist/issues
Keywords: beta distribution,four-parameter beta,likelihood estimation,statistics,probability,hydrology
Platform: UNKNOWN
Classifier: Programming Language :: Python :: 3
Classifier: License :: OSI Approved :: MIT License
Classifier: Operating System :: OS Independent
Classifier: Intended Audience :: Science/Research
Classifier: Topic :: Scientific/Engineering :: Mathematics
Requires-Python: >=3.7
License-File: LICENSE
Requires-Dist: numpy
Requires-Dist: scipy
Provides-Extra: dev
Requires-Dist: pytest; extra == "dev"
